xialib/__init__.py
xialib/adaptor.py
xialib/archiver.py
xialib/controller.py
xialib/decoder.py
xialib/depositor.py
xialib/flower.py
xialib/formatter.py
xialib/publisher.py
xialib/service.py
xialib/storer.py
xialib/subscriber.py
xialib/translator.py
xialib/adaptors/__init__.py
xialib/adaptors/json_adaptor.py
xialib/adaptors/sqlite_adaptor.py
xialib/archivers/__init__.py
xialib/archivers/iolist_archiver.py
xialib/controllers/__init__.py
xialib/controllers/basic_controller.py
xialib/decoders/__init__.py
xialib/decoders/basic_decoder.py
xialib/decoders/zip_decoder.py
xialib/depositors/__init__.py
xialib/depositors/file_depositor.py
xialib/flowers/__init__.py
xialib/flowers/basic_flower.py
xialib/flowers/segment_flower.py
xialib/formatters/__init__.py
xialib/formatters/basic_formatter.py
xialib/formatters/csv_formatter.py
xialib/formatters/zst_formatter.py
xialib/publishers/__init__.py
xialib/publishers/basic_publisher.py
xialib/storers/__init__.py
xialib/storers/basic_storer.py
xialib/subscribers/__init__.py
xialib/subscribers/basic_subscriber.py
xialib/translators/__init__.py
xialib/translators/basic_translator.py
xialib/translators/sap_translator.py
xialib-0.3.16.dist-info/LICENSE
xialib-0.3.16.dist-info/METADATA
xialib-0.3.16.dist-info/WHEEL
xialib-0.3.16.dist-info/top_level.txt
xialib-0.3.16.dist-info/RECORD
