Metadata-Version: 2.1
Name: xialib
Version: 0.3.16
Summary: X-I-A Library
Home-page: https://github.com/X-I-A/xialib
Author: Soral
Author-email: soral@x-i-a.com
License: UNKNOWN
Platform: UNKNOWN
Classifier: Programming Language :: Python :: 3
Classifier: License :: OSI Approved :: GNU Affero General Public License v3 or later (AGPLv3+)
Classifier: Operating System :: OS Independent
Requires-Python: >=3.6
